pykson/__init__.py
pykson/generator.py
pykson/pykson_book.generated.py
pykson/sample.py
pykson-0.9.9.8.17.dist-info/LICENSE
pykson-0.9.9.8.17.dist-info/METADATA
pykson-0.9.9.8.17.dist-info/WHEEL
pykson-0.9.9.8.17.dist-info/top_level.txt
pykson-0.9.9.8.17.dist-info/RECORD
