Metadata-Version: 2.1
Name: pykson
Version: 0.9.9.8.17
Summary: Pykson: A JSON Serializer/Deserializer for Python
Home-page: https://github.com/sinarezaei/pykson
Author: Sina Rezaei
Author-email: sinarezaei1991@gmail.com
License: MIT
Platform: UNKNOWN
Classifier: Programming Language :: Python :: 3
Classifier: License :: OSI Approved :: MIT License
Classifier: Operating System :: OS Independent
Requires-Python: >=3.6
License-File: LICENSE
Requires-Dist: pytz (>=2019.3)
Requires-Dist: python-dateutil (>=2.8.0)
Requires-Dist: six (>=1.12.0)
Requires-Dist: jdatetime (>=3.6.2)
